corx/__init__.py
corx/aggregate.py
corx/base.py
corx/bootstrap.py
corx/command.py
corx/dispatcher.py
corx/event.py
corx/query.py
corx/test.py
corx-1.0.0b3.dist-info/LICENSE.txt
corx-1.0.0b3.dist-info/METADATA
corx-1.0.0b3.dist-info/WHEEL
corx-1.0.0b3.dist-info/top_level.txt
corx-1.0.0b3.dist-info/RECORD
