Metadata-Version: 2.1
Name: corx
Version: 1.0.0b3
Summary: Add a short description here!
Home-page: https://github.com/neromantic/corx
Author: Bohdan Kalvasinskyi
Author-email: kalvasinskyib@gmail.com
License: MIT
Project-URL: Documentation, https://neromantic.github.io/corx/index.html
Project-URL: Source, https://github.com/neromantic/corx
Project-URL: Changelog, https://neromantic.github.io/corx/changelog.html
Project-URL: Tracker, https://github.com/neromantic/corx/issues
Project-URL: Releases, https://github.com/neromantic/corx/releases
Keywords: Python package to work with CQRS + ES architecture
Platform: any
Classifier: Development Status :: 4 - Beta
Classifier: Programming Language :: Python
Requires-Python: >=3.9
License-File: LICENSE.txt
Requires-Dist: tox
Requires-Dist: importlib-metadata ; python_version < "3.8"
Provides-Extra: testing
Requires-Dist: setuptools ; extra == 'testing'
